{
  "global": {
    "global": {
      "gray-50": {
        "value": "#f0f0f0",
        "type": "color"
      },
      "gray-100": {
        "value": "#d9d9d9",
        "type": "color"
      },
      "gray-200": {
        "value": "#bfbfbf",
        "type": "color"
      },
      "gray-300": {
        "value": "#a3a3a3",
        "type": "color"
      },
      "gray-400": {
        "value": "#878787",
        "type": "color"
      },
      "gray-500": {
        "value": "#6e6e6e",
        "type": "color"
      },
      "gray-600": {
        "value": "#5a5858",
        "type": "color"
      },
      "gray-700": {
        "value": "#464444",
        "type": "color"
      },
      "gray-800": {
        "value": "#343432",
        "type": "color"
      },
      "gray-900": {
        "value": "#171616",
        "type": "color"
      },
      "cool-gray-50": {
        "value": "#efeff0",
        "type": "color"
      },
      "cool-gray-100": {
        "value": "#d6d8db",
        "type": "color"
      },
      "cool-gray-200": {
        "value": "#bbbfc3",
        "type": "color"
      },
      "cool-gray-300": {
        "value": "#9ea3a9",
        "type": "color"
      },
      "cool-gray-400": {
        "value": "#818892",
        "type": "color"
      },
      "cool-gray-500": {
        "value": "#666e7a",
        "type": "color"
      },
      "cool-gray-600": {
        "value": "#505968",
        "type": "color"
      },
      "cool-gray-700": {
        "value": "#3e4651",
        "type": "color"
      },
      "cool-gray-800": {
        "value": "#30343b",
        "type": "color"
      },
      "cool-gray-900": {
        "value": "#151619",
        "type": "color"
      },
      "blue-50": {
        "value": "#eff1f6",
        "type": "color"
      },
      "blue-100": {
        "value": "#d0d8e7",
        "type": "color"
      },
      "blue-200": {
        "value": "#b1c0dd",
        "type": "color"
      },
      "blue-300": {
        "value": "#89a4d7",
        "type": "color"
      },
      "blue-400": {
        "value": "#5b84d7",
        "type": "color"
      },
      "blue-500": {
        "value": "#2b67e9",
        "type": "color"
      },
      "blue-600": {
        "value": "#2b55b1",
        "type": "color"
      },
      "blue-700": {
        "value": "#27437c",
        "type": "color"
      },
      "blue-800": {
        "value": "#213154",
        "type": "color"
      },
      "blue-900": {
        "value": "#111622",
        "type": "color"
      },
      "purple-50": {
        "value": "#efeff5",
        "type": "color"
      },
      "purple-100": {
        "value": "#d8d6ea",
        "type": "color"
      },
      "purple-200": {
        "value": "#c1bae3",
        "type": "color"
      },
      "purple-300": {
        "value": "#a698e2",
        "type": "color"
      },
      "purple-400": {
        "value": "#9474ec",
        "type": "color"
      },
      "purple-500": {
        "value": "#7c59d4",
        "type": "color"
      },
      "purple-600": {
        "value": "#5f4b9b",
        "type": "color"
      },
      "purple-700": {
        "value": "#4a3d71",
        "type": "color"
      },
      "purple-800": {
        "value": "#362f50",
        "type": "color"
      },
      "purple-900": {
        "value": "#17141f",
        "type": "color"
      },
      "green-50": {
        "value": "#ecf3ed",
        "type": "color"
      },
      "green-100": {
        "value": "#c8e0cc",
        "type": "color"
      },
      "green-200": {
        "value": "#9dcda5",
        "type": "color"
      },
      "green-300": {
        "value": "#5eb573",
        "type": "color"
      },
      "green-400": {
        "value": "#1c9c4d",
        "type": "color"
      },
      "green-500": {
        "value": "#2c7d44",
        "type": "color"
      },
      "green-600": {
        "value": "#2c6339",
        "type": "color"
      },
      "green-700": {
        "value": "#284d30",
        "type": "color"
      },
      "green-800": {
        "value": "#203724",
        "type": "color"
      },
      "green-900": {
        "value": "#101811",
        "type": "color"
      },
      "teal-50": {
        "value": "#eaf1f0",
        "type": "color"
      },
      "teal-100": {
        "value": "#cbdcda",
        "type": "color"
      },
      "teal-200": {
        "value": "#a4c6c1",
        "type": "color"
      },
      "teal-300": {
        "value": "#71ada4",
        "type": "color"
      },
      "teal-400": {
        "value": "#26978c",
        "type": "color"
      },
      "teal-500": {
        "value": "#247a71",
        "type": "color"
      },
      "teal-600": {
        "value": "#29605a",
        "type": "color"
      },
      "teal-700": {
        "value": "#264a46",
        "type": "color"
      },
      "teal-800": {
        "value": "#203734",
        "type": "color"
      },
      "teal-900": {
        "value": "#101818",
        "type": "color"
      },
      "yellow-50": {
        "value": "#f9efd7",
        "type": "color"
      },
      "yellow-100": {
        "value": "#fad689",
        "type": "color"
      },
      "yellow-200": {
        "value": "#f7b418",
        "type": "color"
      },
      "yellow-300": {
        "value": "#ce9927",
        "type": "color"
      },
      "yellow-400": {
        "value": "#aa822c",
        "type": "color"
      },
      "yellow-500": {
        "value": "#87682c",
        "type": "color"
      },
      "yellow-600": {
        "value": "#6b5629",
        "type": "color"
      },
      "yellow-700": {
        "value": "#524224",
        "type": "color"
      },
      "yellow-800": {
        "value": "#3b301c",
        "type": "color"
      },
      "yellow-900": {
        "value": "#1b160e",
        "type": "color"
      },
      "orange-50": {
        "value": "#f9ece1",
        "type": "color"
      },
      "orange-100": {
        "value": "#f9d2b4",
        "type": "color"
      },
      "orange-200": {
        "value": "#faaf75",
        "type": "color"
      },
      "orange-300": {
        "value": "#eb8b3d",
        "type": "color"
      },
      "orange-400": {
        "value": "#bf763b",
        "type": "color"
      },
      "orange-500": {
        "value": "#9b6236",
        "type": "color"
      },
      "orange-600": {
        "value": "#784e30",
        "type": "color"
      },
      "orange-700": {
        "value": "#5d3f28",
        "type": "color"
      },
      "orange-800": {
        "value": "#412e1f",
        "type": "color"
      },
      "orange-900": {
        "value": "#1e1610",
        "type": "color"
      },
      "red-50": {
        "value": "#f8eded",
        "type": "color"
      },
      "red-100": {
        "value": "#f3d3d5",
        "type": "color"
      },
      "red-200": {
        "value": "#f0b2b4",
        "type": "color"
      },
      "red-300": {
        "value": "#ed878c",
        "type": "color"
      },
      "red-400": {
        "value": "#e75566",
        "type": "color"
      },
      "red-500": {
        "value": "#d32246",
        "type": "color"
      },
      "red-600": {
        "value": "#a42d3f",
        "type": "color"
      },
      "red-700": {
        "value": "#7a2a32",
        "type": "color"
      },
      "red-800": {
        "value": "#572328",
        "type": "color"
      },
      "red-900": {
        "value": "#261213",
        "type": "color"
      },
      "pink-50": {
        "value": "#f7eef0",
        "type": "color"
      },
      "pink-100": {
        "value": "#efd2db",
        "type": "color"
      },
      "pink-200": {
        "value": "#eaaec0",
        "type": "color"
      },
      "pink-300": {
        "value": "#e585a3",
        "type": "color"
      },
      "pink-400": {
        "value": "#df5386",
        "type": "color"
      },
      "pink-500": {
        "value": "#ca2b70",
        "type": "color"
      },
      "pink-600": {
        "value": "#9c3059",
        "type": "color"
      },
      "pink-700": {
        "value": "#732b46",
        "type": "color"
      },
      "pink-800": {
        "value": "#512433",
        "type": "color"
      },
      "pink-900": {
        "value": "#211217",
        "type": "color"
      },
      "white": {
        "value": "#ffffff",
        "type": "color"
      },
      "black": {
        "value": "#000000",
        "type": "color"
      }
    },
    "font-family": {
      "base": {
        "value": "Inter",
        "type": "fontFamilies"
      }
    },
    "line-height": {
      "50": {
        "value": "16",
        "type": "lineHeights"
      },
      "100": {
        "value": "20",
        "type": "lineHeights"
      },
      "200": {
        "value": "24",
        "type": "lineHeights"
      },
      "300": {
        "value": "28",
        "type": "lineHeights"
      },
      "400": {
        "value": "32",
        "type": "lineHeights"
      },
      "500": {
        "value": "32",
        "type": "lineHeights"
      },
      "600": {
        "value": "36",
        "type": "lineHeights"
      },
      "700": {
        "value": "40",
        "type": "lineHeights"
      },
      "800": {
        "value": "48",
        "type": "lineHeights"
      },
      "900": {
        "value": "52",
        "type": "lineHeights"
      },
      "1000": {
        "value": "60",
        "type": "lineHeights"
      }
    },
    "font-weight": {
      "regular": {
        "value": "Regular",
        "type": "fontWeights"
      },
      "medium": {
        "value": "Medium",
        "type": "fontWeights"
      },
      "bold": {
        "value": "Bold",
        "type": "fontWeights"
      }
    },
    "font-size": {
      "50": {
        "value": "12",
        "type": "fontSizes"
      },
      "100": {
        "value": "14",
        "type": "fontSizes"
      },
      "200": {
        "value": "16",
        "type": "fontSizes"
      },
      "300": {
        "value": "18",
        "type": "fontSizes"
      },
      "400": {
        "value": "20",
        "type": "fontSizes"
      },
      "500": {
        "value": "22",
        "type": "fontSizes"
      },
      "600": {
        "value": "25",
        "type": "fontSizes"
      },
      "700": {
        "value": "28",
        "type": "fontSizes"
      },
      "800": {
        "value": "32",
        "type": "fontSizes"
      },
      "900": {
        "value": "36",
        "type": "fontSizes"
      },
      "1000": {
        "value": "40",
        "type": "fontSizes"
      }
    },
    "letter-spacing": {
      "none": {
        "value": "0%",
        "type": "letterSpacing"
      }
    },
    "text-case": {
      "none": {
        "value": "none",
        "type": "textCase"
      }
    },
    "text-decoration": {
      "none": {
        "value": "none",
        "type": "textDecoration"
      }
    },
    "below": {
      "elevation-10": {
        "value": {
          "color": "#11182714",
          "type": "dropShadow",
          "x": "0",
          "y": "2",
          "blur": "4",
          "spread": "0"
        },
        "type": "boxShadow"
      },
      "elevation-20": {
        "value": {
          "color": "#11182714",
          "type": "dropShadow",
          "x": "0",
          "y": "4",
          "blur": "8",
          "spread": "0"
        },
        "type": "boxShadow"
      },
      "elevation-30": {
        "value": {
          "color": "#11182714",
          "type": "dropShadow",
          "x": "0",
          "y": "8",
          "blur": "16",
          "spread": "0"
        },
        "type": "boxShadow"
      },
      "elevation-40": {
        "value": {
          "color": "#11182714",
          "type": "dropShadow",
          "x": "0",
          "y": "16",
          "blur": "32",
          "spread": "0"
        },
        "type": "boxShadow"
      }
    },
    "above": {
      "elevation-10": {
        "value": {
          "color": "#11182714",
          "type": "dropShadow",
          "x": "0",
          "y": "-2",
          "blur": "4",
          "spread": "0"
        },
        "type": "boxShadow"
      },
      "elevation-20": {
        "value": {
          "color": "#11182714",
          "type": "dropShadow",
          "x": "0",
          "y": "-4",
          "blur": "8",
          "spread": "0"
        },
        "type": "boxShadow"
      },
      "elevation-30": {
        "value": {
          "color": "#11182714",
          "type": "dropShadow",
          "x": "0",
          "y": "-8",
          "blur": "16",
          "spread": "0"
        },
        "type": "boxShadow"
      },
      "elevation-40": {
        "value": {
          "color": "#11182714",
          "type": "dropShadow",
          "x": "0",
          "y": "-16",
          "blur": "32",
          "spread": "0"
        },
        "type": "boxShadow"
      }
    },
    "paragraph-spacing": {
      "none": {
        "value": "0",
        "type": "paragraphSpacing"
      }
    },
    "space-0": {
      "value": "0",
      "type": "spacing"
    },
    "space-2": {
      "value": "2",
      "type": "spacing"
    },
    "space-4": {
      "value": "4",
      "type": "spacing"
    },
    "space-8": {
      "value": "8",
      "type": "spacing"
    },
    "space-12": {
      "value": "12",
      "type": "spacing"
    },
    "space-16": {
      "value": "16",
      "type": "spacing"
    },
    "space-20": {
      "value": "20",
      "type": "spacing"
    },
    "space-24": {
      "value": "24",
      "type": "spacing"
    },
    "space-32": {
      "value": "32",
      "type": "spacing"
    },
    "space-40": {
      "value": "40",
      "type": "spacing"
    },
    "space-48": {
      "value": "48",
      "type": "spacing"
    },
    "space-56": {
      "value": "56",
      "type": "spacing"
    },
    "space-64": {
      "value": "64",
      "type": "spacing"
    },
    "space-80": {
      "value": "80",
      "type": "spacing"
    },
    "space-96": {
      "value": "96",
      "type": "spacing"
    },
    "border-radius-0": {
      "value": "0",
      "type": "borderRadius"
    },
    "border-radius-2": {
      "value": "2",
      "type": "borderRadius"
    },
    "border-radius-4": {
      "value": "4",
      "type": "borderRadius"
    },
    "border-radius-8": {
      "value": "8",
      "type": "borderRadius"
    },
    "border-radius-12": {
      "value": "12",
      "type": "borderRadius"
    },
    "border-radius-16": {
      "value": "16",
      "type": "borderRadius"
    },
    "border-radius-20": {
      "value": "20",
      "type": "borderRadius"
    },
    "border-radius-24": {
      "value": "24",
      "type": "borderRadius"
    },
    "border-radius-32": {
      "value": "32",
      "type": "borderRadius"
    },
    "border-radius-40": {
      "value": "40",
      "type": "borderRadius"
    },
    "border-radius-circle": {
      "value": "50%",
      "type": "borderRadius"
    },
    "border-width-0": {
      "value": "0",
      "type": "borderWidth"
    },
    "border-width-10": {
      "value": "1",
      "type": "borderWidth"
    },
    "border-width-20": {
      "value": "2",
      "type": "borderWidth"
    },
    "border-width-30": {
      "value": "4",
      "type": "borderWidth"
    },
    "border-width-40": {
      "value": "8",
      "type": "borderWidth"
    }
  },
  "default": {
    "background": {
      "default": {
        "value": "{global.white}",
        "type": "color",
        "description": ""
      },
      "subdued": {
        "value": "{global.cool-gray-50}",
        "type": "color",
        "description": ""
      },
      "hover": {
        "value": "{global.cool-gray-100}",
        "type": "color",
        "description": ""
      },
      "pressed": {
        "value": "{global.white}",
        "type": "color",
        "description": ""
      },
      "selected": {
        "value": "{global.white}",
        "type": "color",
        "description": ""
      },
      "disabled": {
        "value": "{global.cool-gray-200}",
        "type": "color",
        "description": ""
      },
      "inverse": {
        "value": "{global.cool-gray-900}",
        "type": "color",
        "description": ""
      }
    },
    "border": {
      "default": {
        "value": "{global.cool-gray-100}",
        "type": "color",
        "description": ""
      },
      "subdued": {
        "value": "{global.cool-gray-200}",
        "type": "color",
        "description": ""
      },
      "hover": {
        "value": "{global.cool-gray-100}",
        "type": "color",
        "description": ""
      },
      "pressed": {
        "value": "{global.cool-gray-100}",
        "type": "color",
        "description": ""
      },
      "selected": {
        "value": "{global.cool-gray-100}",
        "type": "color",
        "description": ""
      },
      "disabled": {
        "value": "{global.cool-gray-200}",
        "type": "color",
        "description": ""
      },
      "inverse": {
        "value": "{global.cool-gray-600}",
        "type": "color",
        "description": ""
      }
    },
    "text": {
      "default": {
        "value": "{global.cool-gray-900}",
        "type": "color",
        "description": ""
      },
      "subdued": {
        "value": "{global.cool-gray-500}",
        "type": "color",
        "description": ""
      },
      "hover": {
        "value": "{global.cool-gray-900}",
        "type": "color",
        "description": ""
      },
      "pressed": {
        "value": "{global.cool-gray-900}",
        "type": "color",
        "description": ""
      },
      "selected": {
        "value": "{global.cool-gray-900}",
        "type": "color",
        "description": ""
      },
      "disabled": {
        "value": "{global.cool-gray-300}",
        "type": "color",
        "description": ""
      },
      "inverse": {
        "value": "{global.white}",
        "type": "color",
        "description": ""
      },
      "informative": {
        "value": "{global.blue-500}",
        "type": "color",
        "description": ""
      },
      "success": {
        "value": "{global.green-500}",
        "type": "color",
        "description": ""
      },
      "warning": {
        "value": "{global.yellow-200}",
        "type": "color",
        "description": ""
      },
      "critical": {
        "value": "{global.red-500}",
        "type": "color",
        "description": ""
      }
    },
    "icon": {
      "default": {
        "value": "{global.cool-gray-900}",
        "type": "color",
        "description": ""
      },
      "subdued": {
        "value": "{global.cool-gray-500}",
        "type": "color",
        "description": ""
      },
      "hover": {
        "value": "{global.cool-gray-900}",
        "type": "color",
        "description": ""
      },
      "pressed": {
        "value": "{global.cool-gray-900}",
        "type": "color",
        "description": ""
      },
      "selected": {
        "value": "{global.cool-gray-900}",
        "type": "color",
        "description": ""
      },
      "disabled": {
        "value": "{global.cool-gray-300}",
        "type": "color",
        "description": ""
      },
      "inverse": {
        "value": "{global.white}",
        "type": "color",
        "description": ""
      },
      "informative": {
        "value": "{global.blue-500}",
        "type": "color",
        "description": ""
      },
      "success": {
        "value": "{global.green-500}",
        "type": "color",
        "description": ""
      },
      "warning": {
        "value": "{global.yellow-200}",
        "type": "color",
        "description": ""
      },
      "critical": {
        "value": "{global.red-500}",
        "type": "color",
        "description": ""
      }
    },
    "primary": {
      "default": {
        "value": "{global.blue-500}",
        "type": "color",
        "description": ""
      },
      "subdued": {
        "value": "{global.blue-100}",
        "type": "color",
        "description": ""
      },
      "hover": {
        "value": "{global.blue-600}",
        "type": "color",
        "description": ""
      },
      "pressed": {
        "value": "{global.blue-800}",
        "type": "color",
        "description": ""
      },
      "selected": {
        "value": "{global.blue-800}",
        "type": "color",
        "description": ""
      },
      "disabled": {
        "value": "{global.cool-gray-100}",
        "type": "color",
        "description": ""
      }
    },
    "secondary": {
      "default": {
        "value": "{global.cool-gray-800}",
        "type": "color",
        "description": ""
      },
      "subdued": {
        "value": "{global.cool-gray-100}",
        "type": "color",
        "description": ""
      },
      "hover": {
        "value": "{global.cool-gray-500}",
        "type": "color",
        "description": ""
      },
      "pressed": {
        "value": "{global.cool-gray-900}",
        "type": "color",
        "description": ""
      },
      "selected": {
        "value": "{global.cool-gray-900}",
        "type": "color",
        "description": ""
      },
      "disabled": {
        "value": "{global.cool-gray-100}",
        "type": "color",
        "description": ""
      }
    },
    "neutral": {
      "default": {
        "value": "{global.cool-gray-100}",
        "type": "color",
        "description": ""
      },
      "subdued": {
        "value": "{global.cool-gray-50}",
        "type": "color",
        "description": ""
      },
      "hover": {
        "value": "{global.cool-gray-200}",
        "type": "color",
        "description": ""
      },
      "selected": {
        "value": "{global.cool-gray-300}",
        "type": "color",
        "description": ""
      },
      "pressed": {
        "value": "{global.cool-gray-300}",
        "type": "color",
        "description": ""
      },
      "disabled": {
        "value": "{global.cool-gray-100}",
        "type": "color",
        "description": ""
      }
    },
    "interactive": {
      "default": {
        "value": "{global.cool-gray-100}",
        "type": "color",
        "description": ""
      },
      "hover": {
        "value": "{global.cool-gray-200}",
        "type": "color",
        "description": ""
      },
      "focus": {
        "value": "{global.cool-gray-800}",
        "type": "color",
        "description": ""
      },
      "selected": {
        "value": "{global.cool-gray-900}",
        "type": "color",
        "description": ""
      },
      "error": {
        "value": "{global.red-500}",
        "type": "color",
        "description": ""
      },
      "disabled": {
        "value": "{global.cool-gray-300}",
        "type": "color",
        "description": ""
      }
    },
    "decorative": {
      "informative": {
        "light": {
          "value": "{global.blue-50}",
          "type": "color",
          "description": ""
        },
        "medium": {
          "value": "{global.blue-500}",
          "type": "color",
          "description": ""
        },
        "dark": {
          "value": "{global.blue-700}",
          "type": "color",
          "description": ""
        }
      },
      "success": {
        "light": {
          "value": "{global.green-50}",
          "type": "color",
          "description": ""
        },
        "medium": {
          "value": "{global.green-500}",
          "type": "color",
          "description": ""
        },
        "dark": {
          "value": "{global.green-700}",
          "type": "color",
          "description": ""
        }
      },
      "warning": {
        "light": {
          "value": "{global.yellow-50}",
          "type": "color",
          "description": ""
        },
        "medium": {
          "value": "{global.yellow-200}",
          "type": "color",
          "description": ""
        },
        "dark": {
          "value": "{global.yellow-700}",
          "type": "color",
          "description": ""
        }
      },
      "critical": {
        "light": {
          "value": "{global.red-50}",
          "type": "color",
          "description": ""
        },
        "medium": {
          "value": "{global.red-500}",
          "type": "color",
          "description": ""
        },
        "dark": {
          "value": "{global.red-700}",
          "type": "color",
          "description": ""
        }
      }
    },
    "display": {
      "font-size-xl": {
        "regular": {
          "value": {
            "fontFamily": "{font-family.base}",
            "fontWeight": "{font-weight.regular}",
            "lineHeight": "{line-height.1000}",
            "fontSize": "{font-size.1000}",
            "letterSpacing": "{letter-spacing.none}",
            "paragraphSpacing": "{paragraph-spacing.none}",
            "textCase": "{text-case.none}",
            "textDecoration": "{text-decoration.none}"
          },
          "type": "typography"
        },
        "medium": {
          "value": {
            "fontFamily": "{font-family.base}",
            "fontWeight": "{font-weight.medium}",
            "lineHeight": "{line-height.1000}",
            "fontSize": "{font-size.1000}",
            "letterSpacing": "{letter-spacing.none}",
            "paragraphSpacing": "{paragraph-spacing.none}",
            "textCase": "{text-case.none}",
            "textDecoration": "{text-decoration.none}"
          },
          "type": "typography"
        },
        "bold": {
          "value": {
            "fontFamily": "{font-family.base}",
            "fontWeight": "{font-weight.bold}",
            "lineHeight": "{line-height.1000}",
            "fontSize": "{font-size.1000}",
            "letterSpacing": "{letter-spacing.none}",
            "paragraphSpacing": "{paragraph-spacing.none}",
            "textCase": "{text-case.none}",
            "textDecoration": "{text-decoration.none}"
          },
          "type": "typography"
        }
      },
      "font-size-md": {
        "regular": {
          "value": {
            "fontFamily": "{font-family.base}",
            "fontWeight": "{font-weight.regular}",
            "lineHeight": "{line-height.900}",
            "fontSize": "{font-size.900}",
            "letterSpacing": "{letter-spacing.none}",
            "paragraphSpacing": "{paragraph-spacing.none}",
            "textCase": "{text-case.none}",
            "textDecoration": "{text-decoration.none}"
          },
          "type": "typography"
        },
        "medium": {
          "value": {
            "fontFamily": "{font-family.base}",
            "fontWeight": "{font-weight.medium}",
            "lineHeight": "{line-height.900}",
            "fontSize": "{font-size.900}",
            "letterSpacing": "{letter-spacing.none}",
            "paragraphSpacing": "{paragraph-spacing.none}",
            "textCase": "{text-case.none}",
            "textDecoration": "{text-decoration.none}"
          },
          "type": "typography"
        },
        "bold": {
          "value": {
            "fontFamily": "{font-family.base}",
            "fontWeight": "{font-weight.bold}",
            "lineHeight": "{line-height.900}",
            "fontSize": "{font-size.900}",
            "letterSpacing": "{letter-spacing.none}",
            "paragraphSpacing": "{paragraph-spacing.none}",
            "textCase": "{text-case.none}",
            "textDecoration": "{text-decoration.none}"
          },
          "type": "typography"
        }
      },
      "font-size-sm": {
        "regular": {
          "value": {
            "fontFamily": "{font-family.base}",
            "fontWeight": "{font-weight.regular}",
            "lineHeight": "{line-height.800}",
            "fontSize": "{font-size.800}",
            "letterSpacing": "{letter-spacing.none}",
            "paragraphSpacing": "{paragraph-spacing.none}",
            "textCase": "{text-case.none}",
            "textDecoration": "{text-decoration.none}"
          },
          "type": "typography"
        },
        "medium": {
          "value": {
            "fontFamily": "{font-family.base}",
            "fontWeight": "{font-weight.medium}",
            "lineHeight": "{line-height.800}",
            "fontSize": "{font-size.800}",
            "letterSpacing": "{letter-spacing.none}",
            "paragraphSpacing": "{paragraph-spacing.none}",
            "textCase": "{text-case.none}",
            "textDecoration": "{text-decoration.none}"
          },
          "type": "typography"
        },
        "bold": {
          "value": {
            "fontFamily": "{font-family.base}",
            "fontWeight": "{font-weight.bold}",
            "lineHeight": "{line-height.800}",
            "fontSize": "{font-size.800}",
            "letterSpacing": "{letter-spacing.none}",
            "paragraphSpacing": "{paragraph-spacing.none}",
            "textCase": "{text-case.none}",
            "textDecoration": "{text-decoration.none}"
          },
          "type": "typography"
        }
      }
    },
    "heading": {
      "font-size-2xl": {
        "regular": {
          "value": {
            "fontFamily": "{font-family.base}",
            "fontWeight": "{font-weight.regular}",
            "lineHeight": "{line-height.700}",
            "fontSize": "{font-size.700}",
            "letterSpacing": "{letter-spacing.none}",
            "paragraphSpacing": "{paragraph-spacing.none}",
            "textCase": "{text-case.none}",
            "textDecoration": "{text-decoration.none}"
          },
          "type": "typography"
        },
        "medium": {
          "value": {
            "fontFamily": "{font-family.base}",
            "fontWeight": "{font-weight.medium}",
            "lineHeight": "{line-height.700}",
            "fontSize": "{font-size.700}",
            "letterSpacing": "{letter-spacing.none}",
            "paragraphSpacing": "{paragraph-spacing.none}",
            "textCase": "{text-case.none}",
            "textDecoration": "{text-decoration.none}"
          },
          "type": "typography"
        },
        "bold": {
          "value": {
            "fontFamily": "{font-family.base}",
            "fontWeight": "{font-weight.bold}",
            "lineHeight": "{line-height.700}",
            "fontSize": "{font-size.700}",
            "letterSpacing": "{letter-spacing.none}",
            "paragraphSpacing": "{paragraph-spacing.none}",
            "textCase": "{text-case.none}",
            "textDecoration": "{text-decoration.none}"
          },
          "type": "typography"
        }
      },
      "font-size-xl": {
        "regular": {
          "value": {
            "fontFamily": "{font-family.base}",
            "fontWeight": "{font-weight.regular}",
            "lineHeight": "{line-height.600}",
            "fontSize": "{font-size.600}",
            "letterSpacing": "{letter-spacing.none}",
            "paragraphSpacing": "{paragraph-spacing.none}",
            "textCase": "{text-case.none}",
            "textDecoration": "{text-decoration.none}"
          },
          "type": "typography"
        },
        "medium": {
          "value": {
            "fontFamily": "{font-family.base}",
            "fontWeight": "{font-weight.medium}",
            "lineHeight": "{line-height.600}",
            "fontSize": "{font-size.600}",
            "letterSpacing": "{letter-spacing.none}",
            "paragraphSpacing": "{paragraph-spacing.none}",
            "textCase": "{text-case.none}",
            "textDecoration": "{text-decoration.none}"
          },
          "type": "typography"
        },
        "bold": {
          "value": {
            "fontFamily": "{font-family.base}",
            "fontWeight": "{font-weight.bold}",
            "lineHeight": "{line-height.600}",
            "fontSize": "{font-size.600}",
            "letterSpacing": "{letter-spacing.none}",
            "paragraphSpacing": "{paragraph-spacing.none}",
            "textCase": "{text-case.none}",
            "textDecoration": "{text-decoration.none}"
          },
          "type": "typography"
        }
      },
      "font-size-md": {
        "regular": {
          "value": {
            "fontFamily": "{font-family.base}",
            "fontWeight": "{font-weight.regular}",
            "lineHeight": "{line-height.500}",
            "fontSize": "{font-size.500}",
            "letterSpacing": "{letter-spacing.none}",
            "paragraphSpacing": "{paragraph-spacing.none}",
            "textCase": "{text-case.none}",
            "textDecoration": "{text-decoration.none}"
          },
          "type": "typography"
        },
        "medium": {
          "value": {
            "fontFamily": "{font-family.base}",
            "fontWeight": "{font-weight.medium}",
            "lineHeight": "{line-height.500}",
            "fontSize": "{font-size.500}",
            "letterSpacing": "{letter-spacing.none}",
            "paragraphSpacing": "{paragraph-spacing.none}",
            "textCase": "{text-case.none}",
            "textDecoration": "{text-decoration.none}"
          },
          "type": "typography"
        },
        "bold": {
          "value": {
            "fontFamily": "{font-family.base}",
            "fontWeight": "{font-weight.bold}",
            "lineHeight": "{line-height.500}",
            "fontSize": "{font-size.500}",
            "letterSpacing": "{letter-spacing.none}",
            "paragraphSpacing": "{paragraph-spacing.none}",
            "textCase": "{text-case.none}",
            "textDecoration": "{text-decoration.none}"
          },
          "type": "typography"
        }
      },
      "font-size-sm": {
        "regular": {
          "value": {
            "fontFamily": "{font-family.base}",
            "fontWeight": "{font-weight.regular}",
            "lineHeight": "{line-height.400}",
            "fontSize": "{font-size.400}",
            "letterSpacing": "{letter-spacing.none}",
            "paragraphSpacing": "{paragraph-spacing.none}",
            "textCase": "{text-case.none}",
            "textDecoration": "{text-decoration.none}"
          },
          "type": "typography"
        },
        "medium": {
          "value": {
            "fontFamily": "{font-family.base}",
            "fontWeight": "{font-weight.medium}",
            "lineHeight": "{line-height.400}",
            "fontSize": "{font-size.400}",
            "letterSpacing": "{letter-spacing.none}",
            "paragraphSpacing": "{paragraph-spacing.none}",
            "textCase": "{text-case.none}",
            "textDecoration": "{text-decoration.none}"
          },
          "type": "typography"
        },
        "bold": {
          "value": {
            "fontFamily": "{font-family.base}",
            "fontWeight": "{font-weight.bold}",
            "lineHeight": "{line-height.400}",
            "fontSize": "{font-size.400}",
            "letterSpacing": "{letter-spacing.none}",
            "paragraphSpacing": "{paragraph-spacing.none}",
            "textCase": "{text-case.none}",
            "textDecoration": "{text-decoration.none}"
          },
          "type": "typography"
        }
      }
    },
    "paragraph": {
      "font-size-2xl": {
        "regular": {
          "value": {
            "fontFamily": "{font-family.base}",
            "fontWeight": "{font-weight.regular}",
            "lineHeight": "{line-height.300}",
            "fontSize": "{font-size.300}",
            "letterSpacing": "{letter-spacing.none}",
            "paragraphSpacing": "{paragraph-spacing.none}",
            "textCase": "{text-case.none}",
            "textDecoration": "{text-decoration.none}"
          },
          "type": "typography"
        },
        "medium": {
          "value": {
            "fontFamily": "{font-family.base}",
            "fontWeight": "{font-weight.medium}",
            "lineHeight": "{line-height.300}",
            "fontSize": "{font-size.300}",
            "letterSpacing": "{letter-spacing.none}",
            "paragraphSpacing": "{paragraph-spacing.none}",
            "textCase": "{text-case.none}",
            "textDecoration": "{text-decoration.none}"
          },
          "type": "typography"
        },
        "bold": {
          "value": {
            "fontFamily": "{font-family.base}",
            "fontWeight": "{font-weight.bold}",
            "lineHeight": "{line-height.300}",
            "fontSize": "{font-size.300}",
            "letterSpacing": "{letter-spacing.none}",
            "paragraphSpacing": "{paragraph-spacing.none}",
            "textCase": "{text-case.none}",
            "textDecoration": "{text-decoration.none}"
          },
          "type": "typography"
        }
      },
      "font-size-xl": {
        "regular": {
          "value": {
            "fontFamily": "{font-family.base}",
            "fontWeight": "{font-weight.regular}",
            "lineHeight": "{line-height.200}",
            "fontSize": "{font-size.200}",
            "letterSpacing": "{letter-spacing.none}",
            "paragraphSpacing": "{paragraph-spacing.none}",
            "textCase": "{text-case.none}",
            "textDecoration": "{text-decoration.none}"
          },
          "type": "typography"
        },
        "medium": {
          "value": {
            "fontFamily": "{font-family.base}",
            "fontWeight": "{font-weight.medium}",
            "lineHeight": "{line-height.200}",
            "fontSize": "{font-size.200}",
            "letterSpacing": "{letter-spacing.none}",
            "paragraphSpacing": "{paragraph-spacing.none}",
            "textCase": "{text-case.none}",
            "textDecoration": "{text-decoration.none}"
          },
          "type": "typography"
        },
        "bold": {
          "value": {
            "fontFamily": "{font-family.base}",
            "fontWeight": "{font-weight.bold}",
            "lineHeight": "{line-height.200}",
            "fontSize": "{font-size.200}",
            "letterSpacing": "{letter-spacing.none}",
            "paragraphSpacing": "{paragraph-spacing.none}",
            "textCase": "{text-case.none}",
            "textDecoration": "{text-decoration.none}"
          },
          "type": "typography"
        }
      },
      "font-size-md": {
        "regular": {
          "value": {
            "fontFamily": "{font-family.base}",
            "fontWeight": "{font-weight.regular}",
            "lineHeight": "{line-height.100}",
            "fontSize": "{font-size.100}",
            "letterSpacing": "{letter-spacing.none}",
            "paragraphSpacing": "{paragraph-spacing.none}",
            "textCase": "{text-case.none}",
            "textDecoration": "{text-decoration.none}"
          },
          "type": "typography"
        },
        "medium": {
          "value": {
            "fontFamily": "{font-family.base}",
            "fontWeight": "{font-weight.medium}",
            "lineHeight": "{line-height.100}",
            "fontSize": "{font-size.100}",
            "letterSpacing": "{letter-spacing.none}",
            "paragraphSpacing": "{paragraph-spacing.none}",
            "textCase": "{text-case.none}",
            "textDecoration": "{text-decoration.none}"
          },
          "type": "typography"
        },
        "bold": {
          "value": {
            "fontFamily": "{font-family.base}",
            "fontWeight": "{font-weight.bold}",
            "lineHeight": "{line-height.100}",
            "fontSize": "{font-size.100}",
            "letterSpacing": "{letter-spacing.none}",
            "paragraphSpacing": "{paragraph-spacing.none}",
            "textCase": "{text-case.none}",
            "textDecoration": "{text-decoration.none}"
          },
          "type": "typography"
        }
      },
      "font-size-sm": {
        "regular": {
          "value": {
            "fontFamily": "{font-family.base}",
            "fontWeight": "{font-weight.regular}",
            "lineHeight": "{line-height.50}",
            "fontSize": "{font-size.50}",
            "letterSpacing": "{letter-spacing.none}",
            "paragraphSpacing": "{paragraph-spacing.none}",
            "textCase": "{text-case.none}",
            "textDecoration": "{text-decoration.none}"
          },
          "type": "typography"
        },
        "medium": {
          "value": {
            "fontFamily": "{font-family.base}",
            "fontWeight": "{font-weight.medium}",
            "lineHeight": "{line-height.50}",
            "fontSize": "{font-size.50}",
            "letterSpacing": "{letter-spacing.none}",
            "paragraphSpacing": "{paragraph-spacing.none}",
            "textCase": "{text-case.none}",
            "textDecoration": "{text-decoration.none}"
          },
          "type": "typography"
        },
        "bold": {
          "value": {
            "fontFamily": "{font-family.base}",
            "fontWeight": "{font-weight.bold}",
            "lineHeight": "{line-height.50}",
            "fontSize": "{font-size.50}",
            "letterSpacing": "{letter-spacing.none}",
            "paragraphSpacing": "{paragraph-spacing.none}",
            "textCase": "{text-case.none}",
            "textDecoration": "{text-decoration.none}"
          },
          "type": "typography"
        }
      }
    },
    "below": {
      "elevation-10": {
        "value": {
          "color": "#11182714",
          "type": "dropShadow",
          "x": "0",
          "y": "2",
          "blur": "4",
          "spread": "0"
        },
        "type": "boxShadow"
      },
      "elevation-20": {
        "value": {
          "color": "#11182714",
          "type": "dropShadow",
          "x": "0",
          "y": "4",
          "blur": "8",
          "spread": "0"
        },
        "type": "boxShadow"
      },
      "elevation-30": {
        "value": {
          "color": "#11182714",
          "type": "dropShadow",
          "x": "0",
          "y": "8",
          "blur": "16",
          "spread": "0"
        },
        "type": "boxShadow"
      },
      "elevation-40": {
        "value": {
          "color": "#11182714",
          "type": "dropShadow",
          "x": "0",
          "y": "16",
          "blur": "32",
          "spread": "0"
        },
        "type": "boxShadow"
      }
    },
    "above": {
      "elevation-10": {
        "value": {
          "color": "#11182714",
          "type": "dropShadow",
          "x": "0",
          "y": "-2",
          "blur": "4",
          "spread": "0"
        },
        "type": "boxShadow"
      },
      "elevation-20": {
        "value": {
          "color": "#11182714",
          "type": "dropShadow",
          "x": "0",
          "y": "-4",
          "blur": "8",
          "spread": "0"
        },
        "type": "boxShadow"
      },
      "elevation-30": {
        "value": {
          "color": "#11182714",
          "type": "dropShadow",
          "x": "0",
          "y": "-8",
          "blur": "16",
          "spread": "0"
        },
        "type": "boxShadow"
      },
      "elevation-40": {
        "value": {
          "color": "#11182714",
          "type": "dropShadow",
          "x": "0",
          "y": "-16",
          "blur": "32",
          "spread": "0"
        },
        "type": "boxShadow"
      }
    }
  },
  "dark": {
    "background": {
      "default": {
        "value": "{global.cool-gray-900}",
        "type": "color",
        "description": ""
      },
      "subdued": {
        "value": "{global.cool-gray-50}",
        "type": "color",
        "description": ""
      },
      "hover": {
        "value": "{global.cool-gray-100}",
        "type": "color",
        "description": ""
      },
      "pressed": {
        "value": "{global.white}",
        "type": "color",
        "description": ""
      },
      "selected": {
        "value": "{global.white}",
        "type": "color",
        "description": ""
      },
      "disabled": {
        "value": "{global.cool-gray-200}",
        "type": "color",
        "description": ""
      },
      "inverse": {
        "value": "{global.white}",
        "type": "color",
        "description": ""
      }
    },
    "border": {
      "default": {
        "value": "{global.cool-gray-600}",
        "type": "color",
        "description": ""
      },
      "subdued": {
        "value": "{global.cool-gray-200}",
        "type": "color",
        "description": ""
      },
      "hover": {
        "value": "{global.cool-gray-100}",
        "type": "color",
        "description": ""
      },
      "pressed": {
        "value": "{global.cool-gray-100}",
        "type": "color",
        "description": ""
      },
      "selected": {
        "value": "{global.cool-gray-100}",
        "type": "color",
        "description": ""
      },
      "disabled": {
        "value": "{global.cool-gray-200}",
        "type": "color",
        "description": ""
      },
      "inverse": {
        "value": "{global.cool-gray-100}",
        "type": "color",
        "description": ""
      }
    },
    "text": {
      "default": {
        "value": "{global.white}",
        "type": "color",
        "description": ""
      },
      "subdued": {
        "value": "{global.cool-gray-500}",
        "type": "color",
        "description": ""
      },
      "hover": {
        "value": "{global.cool-gray-900}",
        "type": "color",
        "description": ""
      },
      "pressed": {
        "value": "{global.cool-gray-900}",
        "type": "color",
        "description": ""
      },
      "selected": {
        "value": "{global.cool-gray-900}",
        "type": "color",
        "description": ""
      },
      "disabled": {
        "value": "{global.cool-gray-300}",
        "type": "color",
        "description": ""
      },
      "inverse": {
        "value": "{global.cool-gray-900}",
        "type": "color",
        "description": ""
      },
      "informative": {
        "value": "{global.blue-500}",
        "type": "color",
        "description": ""
      },
      "success": {
        "value": "{global.green-500}",
        "type": "color",
        "description": ""
      },
      "warning": {
        "value": "{global.yellow-200}",
        "type": "color",
        "description": ""
      },
      "critical": {
        "value": "{global.red-500}",
        "type": "color",
        "description": ""
      }
    },
    "icon": {
      "default": {
        "value": "{global.white}",
        "type": "color",
        "description": ""
      },
      "subdued": {
        "value": "{global.cool-gray-500}",
        "type": "color",
        "description": ""
      },
      "hover": {
        "value": "{global.cool-gray-900}",
        "type": "color",
        "description": ""
      },
      "pressed": {
        "value": "{global.cool-gray-900}",
        "type": "color",
        "description": ""
      },
      "selected": {
        "value": "{global.cool-gray-900}",
        "type": "color",
        "description": ""
      },
      "disabled": {
        "value": "{global.cool-gray-300}",
        "type": "color",
        "description": ""
      },
      "inverse": {
        "value": "{global.cool-gray-900}",
        "type": "color",
        "description": ""
      },
      "informative": {
        "value": "{global.blue-500}",
        "type": "color",
        "description": ""
      },
      "success": {
        "value": "{global.green-500}",
        "type": "color",
        "description": ""
      },
      "warning": {
        "value": "{global.yellow-200}",
        "type": "color",
        "description": ""
      },
      "critical": {
        "value": "{global.red-500}",
        "type": "color",
        "description": ""
      }
    },
    "primary": {
      "default": {
        "value": "{global.blue-500}",
        "type": "color",
        "description": ""
      },
      "subdued": {
        "value": "{global.blue-100}",
        "type": "color",
        "description": ""
      },
      "hover": {
        "value": "{global.blue-600}",
        "type": "color",
        "description": ""
      },
      "pressed": {
        "value": "{global.blue-800}",
        "type": "color",
        "description": ""
      },
      "selected": {
        "value": "{global.blue-800}",
        "type": "color",
        "description": ""
      },
      "disabled": {
        "value": "{global.cool-gray-100}",
        "type": "color",
        "description": ""
      }
    },
    "secondary": {
      "default": {
        "value": "{global.cool-gray-800}",
        "type": "color",
        "description": ""
      },
      "subdued": {
        "value": "{global.cool-gray-100}",
        "type": "color",
        "description": ""
      },
      "hover": {
        "value": "{global.cool-gray-500}",
        "type": "color",
        "description": ""
      },
      "pressed": {
        "value": "{global.cool-gray-900}",
        "type": "color",
        "description": ""
      },
      "selected": {
        "value": "{global.cool-gray-900}",
        "type": "color",
        "description": ""
      },
      "disabled": {
        "value": "{global.cool-gray-100}",
        "type": "color",
        "description": ""
      }
    },
    "neutral": {
      "default": {
        "value": "{global.cool-gray-100}",
        "type": "color",
        "description": ""
      },
      "subdued": {
        "value": "{global.cool-gray-50}",
        "type": "color",
        "description": ""
      },
      "hover": {
        "value": "{global.cool-gray-200}",
        "type": "color",
        "description": ""
      },
      "selected": {
        "value": "{global.cool-gray-300}",
        "type": "color",
        "description": ""
      },
      "pressed": {
        "value": "{global.cool-gray-300}",
        "type": "color",
        "description": ""
      },
      "disabled": {
        "value": "{global.cool-gray-100}",
        "type": "color",
        "description": ""
      }
    },
    "interactive": {
      "default": {
        "value": "{global.cool-gray-100}",
        "type": "color",
        "description": ""
      },
      "hover": {
        "value": "{global.cool-gray-200}",
        "type": "color",
        "description": ""
      },
      "focus": {
        "value": "{global.cool-gray-800}",
        "type": "color",
        "description": ""
      },
      "selected": {
        "value": "{global.cool-gray-900}",
        "type": "color",
        "description": ""
      },
      "error": {
        "value": "{global.red-500}",
        "type": "color",
        "description": ""
      },
      "disabled": {
        "value": "{global.cool-gray-300}",
        "type": "color",
        "description": ""
      }
    },
    "decorative": {
      "informative": {
        "light": {
          "value": "{global.blue-50}",
          "type": "color",
          "description": ""
        },
        "medium": {
          "value": "{global.blue-500}",
          "type": "color",
          "description": ""
        },
        "dark": {
          "value": "{global.blue-700}",
          "type": "color",
          "description": ""
        }
      },
      "success": {
        "light": {
          "value": "{global.green-50}",
          "type": "color",
          "description": ""
        },
        "medium": {
          "value": "{global.green-500}",
          "type": "color",
          "description": ""
        },
        "dark": {
          "value": "{global.green-700}",
          "type": "color",
          "description": ""
        }
      },
      "warning": {
        "light": {
          "value": "{global.yellow-50}",
          "type": "color",
          "description": ""
        },
        "medium": {
          "value": "{global.yellow-200}",
          "type": "color",
          "description": ""
        },
        "dark": {
          "value": "{global.yellow-700}",
          "type": "color",
          "description": ""
        }
      },
      "critical": {
        "light": {
          "value": "{global.red-50}",
          "type": "color",
          "description": ""
        },
        "medium": {
          "value": "{global.red-500}",
          "type": "color",
          "description": ""
        },
        "dark": {
          "value": "{global.red-700}",
          "type": "color",
          "description": ""
        }
      }
    }
  }
}